{
  "city_slug": "quetta",
  "n_observations": 731,
  "alert_threshold": 0.5,
  "precision_top1": {
    "k_pct": 0.01,
    "n_top": 7,
    "precision": 0.4286,
    "n_true_pos": 3
  },
  "precision_top5": {
    "k_pct": 0.05,
    "n_top": 36,
    "precision": 0.4167,
    "n_true_pos": 15
  },
  "precision_top10": {
    "k_pct": 0.1,
    "n_top": 73,
    "precision": 0.4521,
    "n_true_pos": 33
  },
  "event_recall": {
    "n_events": 0,
    "n_detected": 0,
    "recall": 0.0,
    "missed_events": [],
    "detected_events": []
  },
  "lead_time": {
    "n_events_with_lead": 0,
    "mean_days": 0.0,
    "median_days": 0.0,
    "p90_days": 0.0,
    "max_days": 0.0,
    "by_event": {}
  },
  "false_alarm": {
    "false_alarms": 58,
    "total_alerts": 106,
    "far_per_100": 54.72,
    "by_month": {
      "1": 66.67,
      "2": 45.45,
      "3": 36.67,
      "4": 50.0,
      "5": 0.0,
      "6": 0.0,
      "7": 100.0,
      "8": 28.57,
      "9": 100.0,
      "10": 0.0,
      "11": 80.0,
      "12": 83.33
    },
    "by_season": {
      "Winter": 63.83,
      "Spring": 40.48,
      "Monsoon": 58.33,
      "Autumn": 80.0
    }
  },
  "alert_stability": {
    "oscillation_count": 57,
    "volatility_score": 0.0781,
    "n_single_day_spikes": 5
  },
  "persistence": {
    "n_events_assessed": 0,
    "mean_persistence": 0.0,
    "median_persistence": 0.0,
    "p10_persistence": 0.0,
    "by_event": {}
  }
}